acppred/__init__.py
acppred/inf.py
acppred/model/ResNet.py
acppred/model/__init__.py
acppred/model/attention_encoder.py
acppred/model/cnn.py
acppred/model/lstm.py
acppred/model_old/ResNet.py
acppred/model_old/__init__.py
acppred/model_old/attention_encoder.py
acppred/model_old/cnn.py
acppred/model_old/lstm.py
acppred-0.0.3.dist-info/METADATA
acppred-0.0.3.dist-info/WHEEL
acppred-0.0.3.dist-info/top_level.txt
acppred-0.0.3.dist-info/RECORD
